pinjected/__init__.py
pinjected/__main__.py
pinjected/decoration.py
pinjected/demo.py
pinjected/dependency_graph_builder.py
pinjected/dependency_graph_description.py
pinjected/exception_util.py
pinjected/exceptions.py
pinjected/global_configs.py
pinjected/graph_inspection.py
pinjected/helper_structure.py
pinjected/helpers.py
pinjected/logging_helper.py
pinjected/main_impl.py
pinjected/maybe_patch.py
pinjected/meta_main.py
pinjected/module_helper.py
pinjected/module_inspector.py
pinjected/module_var_path.py
pinjected/notification.py
pinjected/nx_graph_util.py
pinjected/pinjected_logging.py
pinjected/providable.py
pinjected/run_config_utils.py
pinjected/run_config_utils_v2.py
pinjected/runnables.py
pinjected/visualize_di.py
pinjected/with_context.py
pinjected/_dev_tools/__init__.py
pinjected/cli_visualizations/__init__.py
pinjected/cli_visualizations/tree.py
pinjected/common/__init__.py
pinjected/common/callbacks.py
pinjected/compatibility/__init__.py
pinjected/compatibility/task_group.py
pinjected/di/__init__.py
pinjected/di/app_designed.py
pinjected/di/app_injected.py
pinjected/di/applicative.py
pinjected/di/args_modifier.py
pinjected/di/async_injected.py
pinjected/di/bindings.py
pinjected/di/decorators.py
pinjected/di/design.py
pinjected/di/design_bind_contextx.py
pinjected/di/design_interface.py
pinjected/di/designed.py
pinjected/di/dynamic_proxy.py
pinjected/di/expr_util.py
pinjected/di/func_util.py
pinjected/di/graph.py
pinjected/di/implicit_globals.py
pinjected/di/injected.py
pinjected/di/injected_analysis.py
pinjected/di/iproxy.py
pinjected/di/modular_injected.py
pinjected/di/monadic.py
pinjected/di/overload_experimental.py
pinjected/di/partially_injected.py
pinjected/di/provider.py
pinjected/di/proxiable.py
pinjected/di/session.py
pinjected/di/sessioned.py
pinjected/di/static_method_impl.py
pinjected/di/static_proxy.py
pinjected/di/test_ast.py
pinjected/di/test_dynamic_proxy.py
pinjected/di/test_graph.py
pinjected/di/test_injected.py
pinjected-0.2.252.dist-info/METADATA
pinjected-0.2.252.dist-info/WHEEL
pinjected-0.2.252.dist-info/entry_points.txt
pinjected-0.2.252.dist-info/licenses/LICENSE
pinjected-0.2.252.dist-info/RECORD
